hql_parser/__init__.py
hql_parser/hql_parser.py
hql_parser-0.0.7.dist-info/METADATA
hql_parser-0.0.7.dist-info/WHEEL
hql_parser-0.0.7.dist-info/top_level.txt
hql_parser-0.0.7.dist-info/RECORD
