Metadata-Version: 2.1
Name: hql_parser
Version: 0.0.7
Summary: Parsing DDL files of HIVE
Home-page: https://gitlab.com/hrosmendez/hql_parser
Author: Henry Rosales
Author-email: hrosmendez@gmail.com
Project-URL: Bug Reports, https://gitlab.com/hrosmendez/hql_parser
Project-URL: Funding, https://gitlab.com/hrosmendez/hql_parser
Project-URL: Say Thanks!, https://gitlab.com/hrosmendez/hql_parser
Project-URL: Source, https://gitlab.com/hrosmendez/hql_parser
Keywords: parser;sql;hive;ddl
Classifier: Development Status :: 4 - Beta
Classifier: Intended Audience :: Education
Classifier: Topic :: Software Development :: Build Tools
Classifier: Programming Language :: Python :: 3.10
Requires-Python: >=3.4
